netlite/__init__.py
netlite/dataloader_cifar10.py
netlite/dataloader_mnist.py
netlite/layers.py
netlite/loss_functions.py
netlite/neural_network.py
netlite/numba_optional.py
netlite/optimizer.py
netlite-1.0.3.dist-info/METADATA
netlite-1.0.3.dist-info/WHEEL
netlite-1.0.3.dist-info/licenses/LICENSE
netlite-1.0.3.dist-info/RECORD
