Metadata-Version: 2.4
Name: netlite
Version: 1.0.3
Summary: A small white-box training framework for neural networks for education.
Project-URL: Homepage, https://github.com/haho12/netlite
Project-URL: Issues, https://github.com/haho12/netlite/issues
Author-email: Hanno Homann <hanno.homann@example.com>
License-Expression: MIT
License-File: LICENSE
Classifier: Operating System :: OS Independent
Classifier: Programming Language :: Python :: 3
Requires-Python: >=3.9
Requires-Dist: matplotlib
Requires-Dist: numba
Requires-Dist: numpy
Requires-Dist: scipy
